IFT/IFTBOM.py
IFT/IFTBase.py
IFT/IFTMachine.py
IFT/IFTMachiningFeature.py
IFT/IFTMachiningPart.py
IFT/IFTOperation.py
IFT/IFTPDF.py
IFT/IFTPmi.py
IFT/IFTTool.py
IFT/__init__.py
IFT/build/cut_number_0.csv
IFT/build/intersection_points_0.csv
IFT/build/points_of_ipw_0.csv
IFT/build/toolpath_points_0.csv
IFT/static/A4_template_cam_setup.prt
IFT/static/A4_template_part.prt
IFT/static/configuration.json
IFT/static/featuretypes.txt
IFT/static/tool_ug_type_map.json
ift4aixpath-0.0.3.dist-info/LICENSE
ift4aixpath-0.0.3.dist-info/METADATA
ift4aixpath-0.0.3.dist-info/WHEEL
ift4aixpath-0.0.3.dist-info/top_level.txt
ift4aixpath-0.0.3.dist-info/RECORD
