Metadata-Version: 2.1
Name: ift4aixpath
Version: 0.0.3
Summary: API that uses the NXOpen API to retrieve important CAD-CAM Data from Siemens NX
Author: Lea Tonejca
Author-email: julian.zulehner@gmail.com
Keywords: IFT,CAM,CAD,Data,NXOpen
Requires-Python: ==3.10.*
License-File: LICENSE
Requires-Dist: pymongo
Requires-Dist: numpy
Requires-Dist: matplotlib
